MANIFEST.in
README.md
setup.py
management_commands/__init__.py
management_commands/command.py
management_commands/py.typed
management_commands/utils.py
management_commands.egg-info/PKG-INFO
management_commands.egg-info/SOURCES.txt
management_commands.egg-info/dependency_links.txt
management_commands.egg-info/top_level.txt