Metadata-Version: 1.1
Name: management-commands
Version: 0.5
Summary: Extra small zero-dependency management commands library for python apps
Home-page: https://github.com/a1fred/management_commands
Author: a1fred
Author-email: demalf@gmail.com
License: MIT
Platform: UNKNOWN
Classifier: Environment :: Console
Classifier: Operating System :: POSIX :: Linux
Classifier: Operating System :: MacOS :: MacOS X
Classifier: Development Status :: 4 - Beta
Classifier: Programming Language :: Python :: 3
